{
	"name": "DF_Most_Viewed_Products",
	"properties": {
		"folder": {
			"name": "Misumi"
		},
		"type": "MappingDataFlow",
		"typeProperties": {
			"sources": [
				{
					"dataset": {
						"referenceName": "DS_SQL",
						"type": "DatasetReference"
					},
					"name": "InputTable"
				}
			],
			"sinks": [
				{
					"dataset": {
						"referenceName": "DS_SQL",
						"type": "DatasetReference"
					},
					"name": "TableOutput"
				}
			],
			"transformations": [
				{
					"name": "SortByPageView"
				},
				{
					"name": "SelectColumns"
				}
			],
			"scriptLines": [
				"source(output(",
				"          departmentCode as string,",
				"          categoryCode as string,",
				"          categoryName as string,",
				"          searchCategoryCode as string,",
				"          seriesCode as string,",
				"          seriesName as string,",
				"          brandCode as string,",
				"          brandUrlCode as string,",
				"          brandName as string,",
				"          productImageList as string,",
				"          catchCopy as string,",
				"          minPiecesPerPackage as string,",
				"          maxPiecesPerPackage as string,",
				"          minStandardDaysToShip as string,",
				"          maxStandardDaysToShip as string,",
				"          minStandardUnitPrice as string,",
				"          maxStandardUnitPrice as string,",
				"          minPricePerPiece as string,",
				"          maxPricePerPiece as string,",
				"          recommendFlag as string,",
				"          volumeDiscountFlag as string,",
				"          discontinuedProductFlag as string,",
				"          stock as string,",
				"          pageView as integer,",
				"          comparisonSpecValueList as string,",
				"          shaftPatternSpecValueList as string,",
				"          categoryList as string,",
				"          ID as integer",
				"     ),",
				"     allowSchemaDrift: true,",
				"     validateSchema: false,",
				"     isolationLevel: 'READ_UNCOMMITTED',",
				"     format: 'table') ~> InputTable",
				"InputTable sort(desc(pageView, false),",
				"     caseInsensitive: true) ~> SortByPageView",
				"SortByPageView select(mapColumn(",
				"          ID,",
				"          categoryName,",
				"          seriesName,",
				"          brandName,",
				"          minPricePerPiece,",
				"          maxPricePerPiece,",
				"          volumeDiscountFlag,",
				"          discontinuedProductFlag,",
				"          stock,",
				"          pageView,",
				"          categoryList",
				"     ),",
				"     skipDuplicateMapInputs: true,",
				"     skipDuplicateMapOutputs: true) ~> SelectColumns",
				"SelectColumns sink(allowSchemaDrift: true,",
				"     validateSchema: false,",
				"     deletable:false,",
				"     insertable:true,",
				"     updateable:false,",
				"     upsertable:false,",
				"     recreate:true,",
				"     format: 'table',",
				"     skipDuplicateMapInputs: true,",
				"     skipDuplicateMapOutputs: true,",
				"     errorHandlingOption: 'stopOnFirstError') ~> TableOutput"
			]
		}
	}
}